gradio_leaderboard/__init__.py
gradio_leaderboard/leaderboard.py
gradio_leaderboard/leaderboard.pyi
gradio_leaderboard/templates/component/Index-CzS_eGV6.js
gradio_leaderboard/templates/component/_basePickBy-CPQEc5fh.js
gradio_leaderboard/templates/component/_baseUniq-DlEwemC3.js
gradio_leaderboard/templates/component/arc-4UNMf6Jv.js
gradio_leaderboard/templates/component/architectureDiagram-NQ2NVSRB-ClVp_eQQ.js
gradio_leaderboard/templates/component/blockDiagram-PHRCVELO-CBZHEIQE.js
gradio_leaderboard/templates/component/c4Diagram-6F6E4RAY-BcEP_NdH.js
gradio_leaderboard/templates/component/channel-BK2Jce3b.js
gradio_leaderboard/templates/component/chunk-353BL4L5-D4dVjjbU.js
gradio_leaderboard/templates/component/chunk-67H74DCK-Dd9cOxfN.js
gradio_leaderboard/templates/component/chunk-6OLS64BW-CfumlcA2.js
gradio_leaderboard/templates/component/chunk-AACKK3MU-4CpiDhxa.js
gradio_leaderboard/templates/component/chunk-BFAMUDN2-C6YyJRb4.js
gradio_leaderboard/templates/component/chunk-E2GYISFI-CbYUJnri.js
gradio_leaderboard/templates/component/chunk-QEP2MXWD-BYLoFCys.js
gradio_leaderboard/templates/component/chunk-SKB7J2MH-DNiBnZKZ.js
gradio_leaderboard/templates/component/classDiagram-BGRH5UQR-BrG1RRX8.js
gradio_leaderboard/templates/component/classDiagram-v2-O24JOBDK-BrG1RRX8.js
gradio_leaderboard/templates/component/clone-BA6MvtJ3.js
gradio_leaderboard/templates/component/cytoscape.esm-Bdz5CrXX.js
gradio_leaderboard/templates/component/dagre-FFZHY6LT-6RahWHGr.js
gradio_leaderboard/templates/component/defaultLocale-D7EN2tov.js
gradio_leaderboard/templates/component/diagram-3EMPZRKU-DtoOVTDy.js
gradio_leaderboard/templates/component/diagram-5UYTHUR4-MEp0H-U7.js
gradio_leaderboard/templates/component/diagram-ZTM2IBQH-22c5YuUh.js
gradio_leaderboard/templates/component/erDiagram-R3QVA2FD-DZp2MeDc.js
gradio_leaderboard/templates/component/flowDiagram-PKI6S5ZS-CfK9UZi3.js
gradio_leaderboard/templates/component/ganttDiagram-EK5VF46D-waaD2Kup.js
gradio_leaderboard-0.0.14.dist-info/METADATA
gradio_leaderboard-0.0.14.dist-info/WHEEL
gradio_leaderboard-0.0.14.dist-info/RECORD
